[
  {
    "title": "Прозрачные цены",
    "urlSvg": "wallet",
    "descript": "Составление предварительного финансового плана лечения"
  },
  {
    "title": "Ваш комфорт — наш приоритет",
    "urlSvg": "armchair",
    "descript": "Используем современные методики обезболивания: анестезию, наркоз или седацию"
  },
  {
    "title": "Передовые технологии",
    "urlSvg": "tools",
    "descript": "Применяем в работе современное стоматологическое и диагностическое оборудование экспертного уровня"
  },
  {
    "title": "Опыт и репутация",
    "urlSvg": "experience",
    "descript": "С 2002 года оказываем полный спектр стоматологических услуг для всей семьи"
  },
  {
    "title": "Команда профессионалов",
    "urlSvg": "doctors",
    "descript": "К вашим услугам более 100 специалистов, включая кандидатов наук и врачей с международными сертификатами"
  },
  {
    "title": "Развитая сеть клиник",
    "urlSvg": "location",
    "descript": "Принимаем пациентов в 9 стоматологических отделениях в разных районах Москвы"
  },
  {
    "title": "Более 10 000 довольных клиентов",
    "urlSvg": "luckyTooth",
    "descript": "Заботимся о красоте улыбок взрослых и самых маленьких пациентов"
  },
  {
    "title": "Собственная зуботехническая лаборатория",
    "urlSvg": "computer",
    "descript": "Изготавливаем разнообразные зубные конструкции, в том числе повышенной сложности"
  }
]